pychassislib-0.4.4.dist-info/METADATA
pychassislib-0.4.4.dist-info/WHEEL
pychassislib/__init__.py
pychassislib/chassis/__init__.py
pychassislib/chassis/chassis.py
pychassislib/chassis/config.py
pychassislib/chassis/consts.py
pychassislib/mongodb_orm/__init__.py
pychassislib/mongodb_orm/base_document.py
pychassislib/mongodb_orm/mixin_document.py
pychassislib/mongodb_orm/utils.py
pychassislib/namekoproxy_pool/__init__.py
pychassislib/namekoproxy_pool/connection_pool.py
pychassislib/namekoproxy_pool/errors.py
pychassislib/namekoproxy_pool/proxies/__init__.py
pychassislib/namekoproxy_pool/proxies/base_proxy.py
pychassislib/namekoproxy_pool/proxies/flask_proxy.py
pychassislib/redis_orm/__init__.py
pychassislib/redis_orm/redis_conn_pool.py
pychassislib/relationaldb_orm/__init__.py
pychassislib/relationaldb_orm/db_context.py
pychassislib/relationaldb_orm/db_model.py
pychassislib/relationaldb_orm/utils.py
pychassislib-0.4.4.dist-info/RECORD
